max_div/__init__.py
max_div/_cli/__init__.py
max_div/_cli/_cli.py
max_div/_cli/_cmd_benchmark.py
max_div/_cli/_cmd_benchmark_internal.py
max_div/_cli/_cmd_benchmark_solver.py
max_div/_cli/_cmd_benchmark_solver_list_problems.py
max_div/_cli/_cmd_benchmark_solver_presets.py
max_div/_cli/_cmd_benchmark_solver_strategies.py
max_div/_cli/_cmd_numba_status.py
max_div/_cli/_cmd_solve.py
max_div/_cli/bm_internal/__init__.py
max_div/_cli/bm_internal/diversity_metrics.py
max_div/_cli/bm_internal/modify_p_selectivity.py
max_div/_cli/bm_internal/randint.py
max_div/_cli/bm_internal/randint_constrained.py
max_div/_cli/bm_solver_presets/__init__.py
max_div/_cli/bm_solver_presets/_executors.py
max_div/_cli/bm_solver_presets/_models.py
max_div/_cli/bm_solver_presets/_utils.py
max_div/_cli/bm_solver_presets/execute.py
max_div/_cli/bm_solver_presets/scope.py
max_div/_cli/bm_solver_presets/show.py
max_div/_cli/bm_solver_strategies/__init__.py
max_div/_cli/bm_solver_strategies/_base.py
max_div/_cli/bm_solver_strategies/_bm_initialization.py
max_div/_cli/bm_solver_strategies/_bm_optimization.py
max_div/_cli/bm_solver_strategies/main.py
max_div/benchmarks/__init__.py
max_div/benchmarks/_factory.py
max_div/benchmarks/_registry.py
max_div/benchmarks/_problems/__init__.py
max_div/benchmarks/_problems/_helpers.py
max_div/benchmarks/_problems/_problem_c1.py
max_div/benchmarks/_problems/_problem_c2.py
max_div/benchmarks/_problems/_problem_c3.py
max_div/benchmarks/_problems/_problem_c4.py
max_div/benchmarks/_problems/_problem_u1.py
max_div/benchmarks/_problems/_problem_u2.py
max_div/benchmarks/_problems/_problem_u3.py
max_div/benchmarks/_problems/_problem_u4.py
max_div/benchmarks/_strategy_presets/__init__.py
max_div/benchmarks/_strategy_presets/_init_presets.py
max_div/benchmarks/_strategy_presets/_optim_presets.py
max_div/internal/__init__.py
max_div/internal/benchmarking/__init__.py
max_div/internal/benchmarking/_micro_benchmark.py
max_div/internal/benchmarking/_timer.py
max_div-0.5.0.dist-info/METADATA
max_div-0.5.0.dist-info/WHEEL
max_div-0.5.0.dist-info/entry_points.txt
max_div-0.5.0.dist-info/licenses/LICENSE
max_div-0.5.0.dist-info/RECORD
