Metadata-Version: 2.4
Name: max-div
Version: 0.5.0
Summary: Configurable Solver for Maximum Diversity Problems with Fairness Constraints.
Project-URL: Documentation, https://max-div.readthedocs.io/
Project-URL: Source, https://github.com/bertpl/max-div
Project-URL: ChangeLog, https://github.com/bertpl/max-div/blob/main/CHANGELOG.md
Project-URL: Issues, https://github.com/bertpl/max-div/issues
Project-URL: Roadmap, https://github.com/bertpl/max-div/milestones
Author-email: Bert Pluymers <bert.pluymers@gmail.com>
License-File: LICENSE
Requires-Python: >=3.11
Requires-Dist: click>=8.2.0
Requires-Dist: icc-rt; platform_machine == 'x86_64' and platform_system == 'Linux'
Requires-Dist: intel-cmplr-lib-rt; platform_machine == 'x86_64' and platform_system == 'Linux'
Requires-Dist: numba>=0.57
Requires-Dist: numpy>=2.0.0
Requires-Dist: scipy>=1.10.0
Requires-Dist: tqdm>=4.66.0
Provides-Extra: docs
Requires-Dist: mkdocs-autoapi[python]>=0.4.1; extra == 'docs'
Requires-Dist: mkdocs-include-markdown-plugin>=7.2.0; extra == 'docs'
Requires-Dist: mkdocs-material>=9.0.0; extra == 'docs'
Requires-Dist: mkdocs>=1.6.1; extra == 'docs'
Requires-Dist: mkdocstrings[python]>=0.24.0; extra == 'docs'
Requires-Dist: ruff>=0.14.0; extra == 'docs'
